{"business_id": "", "full_address": "16860 Lorain Ave\nCleveland, OH 44111", "hours": {"Friday": {"close": "03:00", "open": "11:00"}, "Tuesday": {"close": "22:00", "open": "11:00"}, "Thursday": {"close": "22:00", "open": "11:00"}, "Wednesday": {"close": "22:00", "open": "11:00"}, "Monday": {"close": "22:00", "open": "11:00"}, {"Saturday": {"close": "03:00", "open": "11:00"}}, "open": true, "categories": ["Greek", "Restaurants"], "city": "Cleveland", "review_count": 38, "name": "Gyro World", "neighborhoods": [], "longitude": -81.8150843, "state": "OH", "stars": 4.5, "latitude": 41.4507503, "attributes": {"Take-out": true, "Drive-Thru": false, "Good For": {"dessert": false, "latenight": true, "lunch": true, "dinner": true, "brunch": false, "breakfast": false}, "Caters": false, "Noise Level": "Average", "Takes Reservations": false, "Delivery": false, "Ambience": {"romantic": false, "intimate": false, "classy": false, "hipster": false, "divey": true, "touristy": false, "trendy": false, "upscale": false, "casual": true}, "Parking": {"garage": false, "street": true, "validated": false, "lot": false, "valet": false}, "Has TV": false, "Outdoor Seating": false, "Attire": "Casual", "Alcohol": "No", "Waiter Service": false, "Accepts Credit Cards": true, "Good for Kids": true, "Good For Groups": true, "Price Range": 1}, "type": "business"}